MANIFEST.in
README.md
inkpath.py
manage_extensions.inx
manage_extensions.py
setup.py
inkman/__init__.py
inkman/__main__.py
inkman/archive.py
inkman/backfoot.py
inkman/factory.py
inkman/package.py
inkman/remote.py
inkman/target.py
inkman/targets.py
inkman/utils.py
inkman/data/__init__.py
inkman/data/gui.glade
inkman/data/info.glade
inkman/data/package.json
inkman/data/pixmaps/__init__.py
inkman/data/pixmaps/core_icon.svg
inkman/data/pixmaps/default.svg
inkman/data/pixmaps/default_icon.svg
inkman/data/pixmaps/docs.png
inkman/data/pixmaps/icon.svg
inkman/data/pixmaps/module_icon.svg
inkman/data/pixmaps/not-found.png
inkman/data/pixmaps/orphan_icon.svg
inkman/data/pixmaps/star-lots.svg
inkman/data/pixmaps/star-none.svg
inkman/data/pixmaps/star-some.svg
inkman/gui/__init__.py
inkman/gui/info.py
inkman/gui/main.py
inkscape_extensions_manager.egg-info/PKG-INFO
inkscape_extensions_manager.egg-info/SOURCES.txt
inkscape_extensions_manager.egg-info/dependency_links.txt
inkscape_extensions_manager.egg-info/requires.txt
inkscape_extensions_manager.egg-info/top_level.txt